paddle_template/__init__.py
paddle_template/config.py
paddle_template/data_processors.py
paddle_template/feature_extractor.py
paddle_template/model.py
paddle_template/schema.py
paddle_template/trainer.py
paddle_template/trainer_nlp.py
paddle_template/trainer_speech.py
paddle_template/utils.py
paddle_template/version.py
tests/__init__.py
tests/test_config.py
tests/test_smoke.py
paddle_template-0.0.2.dist-info/LICENSE
paddle_template-0.0.2.dist-info/METADATA
paddle_template-0.0.2.dist-info/WHEEL
paddle_template-0.0.2.dist-info/top_level.txt
paddle_template-0.0.2.dist-info/RECORD
