Metadata-Version: 2.1
Name: paddle-template
Version: 0.0.2
Summary: the stupid & powerful template for paddle models which can reduce your lots of work
Home-page: https://github.com/wj-Mcat/paddle-template
Author: Jingjing WU (吴京京)
Author-email: wjmcater@gmail.com
License: Apache-2.0
Platform: UNKNOWN
Classifier: Programming Language :: Python :: 3.7
Classifier: License :: OSI Approved :: Apache Software License
Classifier: Operating System :: OS Independent
Requires-Dist: paddlenlp
Requires-Dist: paddlepaddle
Requires-Dist: semver
Requires-Dist: typed-argument-parser
Requires-Dist: numpy
Requires-Dist: dataclasses-json
Requires-Dist: tqdm
Requires-Dist: loguru
Requires-Dist: visualdl
